module OpCodes

  BYTE_NOP = 0
  BYTE_ACONST_NULL = 1 # (0X1)
  BYTE_ICONST_M1 = 2 # (0X2)
  BYTE_ICONST_0 = 3 # (0X3)
  BYTE_ICONST_1 = 4 # (0X4)
  BYTE_ICONST_2 = 5 # (0X5)
  BYTE_ICONST_3 = 6 # (0X6)
  BYTE_ICONST_4 = 7 # (0X7)
  BYTE_ICONST_5 = 8 # (0X8)
  BYTE_LCONST_0 = 9 # (0X9)
  BYTE_LCONST_1 = 10 # (0XA)
  BYTE_FCONST_0 = 11 # (0X0B)
  BYTE_FCONST_1 = 12 # (0X0C)
  BYTE_FCONST_2 = 13 # (0X0D)
  BYTE_DCONST_0 = 14 # (0X0E)
  BYTE_DCONST_1 = 15 # (0X0F)
  BYTE_BIPUSH = 16 # (0X10)
  BYTE_SIPUSH = 17 # (0X11)
  BYTE_LDC = 18 # (0X12)
  BYTE_LDC_W = 19 # (0X13)
  BYTE_LDC2_W = 20 # (0X14)
  BYTE_ILOAD = 21 # (0X15)
  BYTE_LLOAD = 22 # (0X16)
  BYTE_FLOAD = 23 # (0X17)
  BYTE_DLOAD = 24 # (0X18)
  BYTE_ALOAD = 25 # (0X19)
  BYTE_ILOAD_0 = 26 # (0X1A)
  BYTE_ILOAD_1 = 27 # (0X1B)
  BYTE_ILOAD_2 = 28 # (0X1C)
  BYTE_ILOAD_3 = 29 # (0X1D)
  BYTE_LLOAD_0 = 30 # (0X1E)
  BYTE_LLOAD_1 = 31 # (0X1F)
  BYTE_LLOAD_2 = 32 # (0X20)
  BYTE_LLOAD_3 = 33 # (0X21)
  BYTE_FLOAD_0 = 34 # (0X22)
  BYTE_FLOAD_1 = 35 # (0X23)
  BYTE_FLOAD_2 = 36 # (0X24)
  BYTE_FLOAD_3 = 37 # (0X25)
  BYTE_DLOAD_0 = 38 # (0X26)
  BYTE_DLOAD_1 = 39 # (0X27)
  BYTE_DLOAD_2 = 40 # (0X28)
  BYTE_DLOAD_3 = 41 # (0X29)
  BYTE_ALOAD_0 = 42 # (0X2A)
  BYTE_ALOAD_1 = 43 # (0X2B)
  BYTE_ALOAD_2 = 44 # (0X2C)
  BYTE_ALOAD_3 = 45 # (0X2D)
  BYTE_IALOAD = 46 # (0X2E)
  BYTE_LALOAD = 47 # (0X2F)
  BYTE_FALOAD = 48 # (0X30)
  BYTE_DALOAD = 49 # (0X31)
  BYTE_AALOAD = 50 # (0X32)
  BYTE_BALOAD = 51 # (0X33)
  BYTE_CALOAD = 52 # (0X34)
  BYTE_SALOAD = 53 # (0X35)
  BYTE_ISTORE = 54 # (0X36)
  BYTE_LSTORE = 55 # (0X37)
  BYTE_FSTORE = 56 # (0X38)
  BYTE_DSTORE = 57 # (0X39)
  BYTE_ASTORE = 58 # (0X3A)
  BYTE_ISTORE_0 = 59 # (0X3B)
  BYTE_ISTORE_1 = 60 # (0X3C)
  BYTE_ISTORE_2 = 61 # (0X3D)
  BYTE_ISTORE_3 = 62 # (0X3E)
  BYTE_LSTORE_0 = 63 # (0X3F)
  BYTE_LSTORE_1 = 64 # (0X40)
  BYTE_LSTORE_2 = 65 # (0X41)
  BYTE_LSTORE_3 = 66 # (0X42)
  BYTE_FSTORE_0 = 67 # (0X43)
  BYTE_FSTORE_1 = 68 # (0X44)
  BYTE_FSTORE_2 = 69 # (0X45)
  BYTE_FSTORE_3 = 70 # (0X46)
  BYTE_DSTORE_0 = 71 # (0X47)
  BYTE_DSTORE_1 = 72 # (0X48)
  BYTE_DSTORE_2 = 73 # (0X49)
  BYTE_DSTORE_3 = 74 # (0X4A)
  BYTE_ASTORE_0 = 75 # (0X4B)
  BYTE_ASTORE_1 = 76 # (0X4C)
  BYTE_ASTORE_2 = 77 # (0X4D)
  BYTE_ASTORE_3 = 78 # (0X4E)
  BYTE_IASTORE = 79 # (0X4F)
  BYTE_LASTORE = 80 # (0X50)
  BYTE_FASTORE = 81 # (0X51)
  BYTE_DASTORE = 82 # (0X52)
  BYTE_AASTORE = 83 # (0X53)
  BYTE_BASTORE = 84 # (0X54)
  BYTE_CASTORE = 85 # (0X55)
  BYTE_SASTORE = 86 # (0X56)
  BYTE_POP = 87 # (0X57)
  BYTE_POP2 = 88 # (0X58)
  BYTE_DUP = 89 # (0X59)
  BYTE_DUP_X1 = 90 # (0X5A)
  BYTE_DUP_X2 = 91 # (0X5B)
  BYTE_DUP2 = 92 # (0X5C)
  BYTE_DUP2_X1 = 93 # (0X5D)
  BYTE_DUP2_X2 = 94 # (0X5E)
  BYTE_SWAP = 95 # (0X5F)
  BYTE_IADD = 96 # (0X60)
  BYTE_LADD = 97 # (0X61)
  BYTE_FADD = 98 # (0X62)
  BYTE_DADD = 99 # (0X63)
  BYTE_ISUB = 100 # (0X64)
  BYTE_LSUB = 101 # (0X65)
  BYTE_FSUB = 102 # (0X66)
  BYTE_DSUB = 103 # (0X67)
  BYTE_IMUL = 104 # (0X68)
  BYTE_LMUL = 105 # (0X69)
  BYTE_FMUL = 106 # (0X6A)
  BYTE_DMUL = 107 # (0X6B)
  BYTE_IDIV = 108 # (0X6C)
  BYTE_LDIV = 109 # (0X6D)
  BYTE_FDIV = 110 # (0X6E)
  BYTE_DDIV = 111 # (0X6F)
  BYTE_IREM = 112 #(0X70)
  BYTE_LREM = 113 #(0X71)
  BYTE_FREM = 114 #(0X72)
  BYTE_DREM = 115 #(0X73)
  BYTE_INEG = 116 #(0X74)
  BYTE_LNEG = 117 #(0X75)
  BYTE_FNEG = 118 #(0X76)
  BYTE_DNEG = 119 #(0X77)
  BYTE_ISHL = 120 #(0X78)
  BYTE_LSHL = 121 #(0X79)
  BYTE_ISHR = 122 #(0X7A)
  BYTE_LSHR = 123 #(0X7B)
  BYTE_IUSHR = 124 #(0X7C)
  BYTE_LUSHR = 125 #(0X7D)
  BYTE_IAND = 126 #(0X7E)
  BYTE_LAND = 127 #(0X7F)
  BYTE_IOR = 128 #(0X80)
  BYTE_LOR = 129 #(0X81)
  BYTE_IXOR = 130 #(0X82)
  BYTE_LXOR = 131 #(0X83)
  BYTE_IINC = 132 # (0X84)
  BYTE_I2L = 133 #(0X85)
  BYTE_I2F = 134 #(0X86)
  BYTE_I2D = 135 #(0X87)
  BYTE_L2I = 136 #(0X88)
  BYTE_L2F = 137 #(0X89)
  BYTE_L2D = 138 #(0X8A)
  BYTE_F2I = 139 #(0X8B)
  BYTE_F2L = 140 #(0X8C)
  BYTE_F2D = 141 #(0X8D)
  BYTE_D2I = 142 #(0X8E)
  BYTE_D2L = 143 #(0X8F)
  BYTE_D2F = 144 #(0X90)
  BYTE_I2B = 145 #(0X91)
  BYTE_I2C = 146 #(0X92)
  BYTE_I2S = 147 #(0X93)
  BYTE_LCMP = 148 # (0X94)
  BYTE_FCMPL = 149 # (0x95)
  BYTE_FCMPG = 150 # (0x96)
  BYTE_DCMPL = 151 # (0x97)
  BYTE_DCMPG = 152 # (0X98)
  BYTE_IFEQ = 153 # (0X99)
  BYTE_IFNE = 154 # (0X9A)
  BYTE_IFLT = 155 # (0X9B)
  BYTE_IFGE = 156 # (0X9C)
  BYTE_IFGT = 157 # (0X9D)
  BYTE_IFLE = 158 # (0X9E)
  BYTE_IF_ICMPEQ = 159 # (0X9F)
  BYTE_IF_ICMPNE = 160 # (0XA0)
  BYTE_IF_ICMPLT = 161 # (0XA1)
  BYTE_IF_ICMPGE = 162 # (0XA2)
  BYTE_IF_ICMPGT = 163 # (0XA3)
  BYTE_IF_ICMPLE = 164 # (0XA4)
  BYTE_IF_ACMPEQ = 165 # (0XA5)
  BYTE_IF_ACMPNE = 166 # (0XA6)
  BYTE__GOTO = 167 # (0XA7)
  BYTE_JSR = 168 # (0XA8)
  BYTE_RET = 169 # (0XA9)
  BYTE_TABLESWITCH = 170 # (0XAA)
  BYTE_LOOKUPSWITCH = 171 # (0XAB)
  BYTE_IRETURN = 172 # (0XAC)
  BYTE_LRETURN = 173 # (0XAD)
  BYTE_FRETURN = 174 # (0XAE)
  BYTE_DRETURN = 175 # (0XAF)
  BYTE_ARETURN = 176 # (0XB0)
  BYTE__RETURN = 177 # (0XB1)
  BYTE_GETSTATIC = 178 # (0XB2)
  BYTE_PUTSTATIC = 179 # (0XB3)
  BYTE_GETFIELD = 180 # (0XB4)
  BYTE_PUTFIELD = 181 # (0XB5)
  BYTE_INVOKEVIRTUAL = 182 # (0XB6)
  BYTE_INVOKESPECIAL = 183 # (0XB7)
  BYTE_INVOKESTATIC = 184 # (0XB8)
  BYTE_INVOKEINTERFACE = 185 # (0XB9)
  BYTE_INVOKEDYNAMIC = 186 # (0XBA)
  BYTE__NEW = 187 # (0XBB)
  BYTE_NEWARRAY = 188 # (0XBC)
  BYTE_ANEWARRAY = 189 # (0XBD)
  BYTE_ARRAYLENGTH = 190 # (0XBE)
  BYTE_ATHROW = 191 # (0XBF)
  BYTE_CHECKCAST = 192 # (0XC0)
  BYTE_INSTANCEOF = 193 # (0XC1)
  BYTE_MONITORENTER = 194 # (0XC2)
  BYTE_MONITOREXIT = 195 # (0XC3)
  BYTE_WIDE = 196 # (0XC4)
  BYTE_MULTIANEWARRAY = 197 # (0XC5)
  BYTE_IFNULL = 198 # (0XC6)
  BYTE_IFNONNULL = 199 # (0XC7)
  BYTE_GOTO_W = 200 # (0XC8)
  BYTE_JSR_W = 201 # (0XC9)

end